{"1": "Then Bildad the Shuhite responded.", "2": "Bildad: God rules over all things; dread is His domain, God\u2014who makes peace and order on His own heights.", "3": "As for His armies, can they even be counted? As for His light, is anyone not illuminated?", "4": "Then tell me how can a person be right with God? How can someone born of a woman in blood be pure?", "5": "If even the moon is not bright enough and the light of the stars is not pure in His estimation,", "6": "How much less so a human, who is a mere worm\u2014 The offspring of humanity, who is a maggot!"}