{"1": "O God, hasten to deliver me; O Lord, hasten to my help!", "2": "Let those be ashamed and humiliated Who seek my [a]life; Let those be turned back and dishonored Who delight [b]in my hurt.", "3": "Let those be [c]turned back because of their shame Who say, \u201cAha, aha!\u201d", "4": "Let all who seek You rejoice and be glad in You; And let those who love Your salvation say continually, \u201cLet God be magnified.\u201d", "5": "But I am afflicted and needy; Hasten to me, O God! You are my help and my deliverer; O Lord, do not delay."}