{"1": "Hallelujah! Praise the Lord! Praise God in his holy sanctuary! Praise him in his stronghold in the sky!", "2": "Praise him for his miracles of might! Praise him for his magnificent greatness!", "3": "Praise him with the trumpets blasting! Praise him with piano and guitar!", "4-5": "\u20135\u00a0Praise him with drums and dancing! Praise him with the loud, resounding clash of cymbals! Praise him with every instrument you can find!", "6": "Let everyone everywhere join in the crescendo of ecstatic praise to Yahweh! Hallelujah! Praise the Lord!"}