{"1": "Lord, I cry unto Thee! Make haste unto me! Give ear unto my voice when I cry unto Thee.", "2": "Let my prayer be set before Thee as incense, and the lifting up of my hands as the evening sacrifice.", "3": "Set a watch, O Lord, before my mouth; keep the door of my lips.", "4": "Incline not my heart to any evil thing, to practice wicked works with men that work iniquity; and let me not eat of their dainties.", "5": "Let the righteous smite me: it shall be a kindness. And let him reprove me: it shall be as an excellent oil, which shall not break my head; for yet my prayer shall be with them in their calamities.", "6": "When their judges are overthrown onto stony places, they shall hear my words, for they are sweet.", "7": "Our bones are scattered at the grave's mouth, as when one cutteth and cleaveth wood upon the earth.", "8": "But mine eyes are unto Thee, O God the Lord; in Thee is my trust; leave not my soul destitute.", "9": "Keep me from the snares which they have laid for me, and the traps of the workers of iniquity.", "10": "Let the wicked fall into their own nets, whilst I thereupon escape."}