{"1": "O God, Thou hast cast us off, Thou hast scattered us, Thou hast been displeased; O, turn Thyself to us again!", "2": "Thou hast made the earth to tremble, Thou hast broken it; heal the breaches thereof, for it shaketh.", "3": "Thou hast shown Thy people hard things; Thou hast made us to drink the wine of astonishment.", "4": "Thou hast given a banner to them that fear Thee, that it may be displayed because of the truth. Selah", "5": "That Thy beloved may be delivered, save with Thy right hand and hear me!", "6": "God hath spoken in His holiness: \u201cI will rejoice; I will divide Shechem and portion out the Valley of Succoth.", "7": "Gilead is Mine, and Manasseh is Mine; Ephraim also is the strength of Mine head; Judah is My lawgiver.", "8": "Moab is My washpot; over Edom will I cast out My shoe; Philistia, triumph thou because of Me.\u201d", "9": "Who will bring me into the stronghold city? Who will lead me into Edom?", "10": "Will not Thou, O God, who hadst cast us off, and Thou, O God, who didst not go out with our armies?", "11": "Give us help from trouble, for vain is the help of man.", "12": "Through God we shall do valiantly, for He it is that shall tread down our enemies."}